my_tools/__init__.py
my_tools/entrypoint.py
my_tools/models.py
my_tools/sandbox_setup.py
my_tools/utils.py
dkoshman_my_tools-0.1.6.dist-info/LICENSE
dkoshman_my_tools-0.1.6.dist-info/WHEEL
dkoshman_my_tools-0.1.6.dist-info/METADATA
dkoshman_my_tools-0.1.6.dist-info/RECORD
