Metadata-Version: 2.1
Name: dkoshman-my-tools
Version: 0.1.6
Summary: 
Author: DimaKoshman
Author-email: koshmandk@yandex.ru
Requires-Python: >=3.8
Classifier: Programming Language :: Python :: 3
Classifier: Programming Language :: Python :: 3.8
Classifier: Programming Language :: Python :: 3.9
Classifier: Programming Language :: Python :: 3.10
Requires-Dist: einops (>=0.4.1,<0.5.0)
Requires-Dist: numba (>=0.56.2,<0.57.0)
Requires-Dist: numpy (>=1.22,<2.0)
Requires-Dist: pandas (>=1.4.0,<2.0.0)
Requires-Dist: pytest (>=7.1.3,<8.0.0)
Requires-Dist: pytorch-lightning (>=1.6,<2.0)
Requires-Dist: scikit-learn (>=1.2.0,<2.0.0)
Requires-Dist: scipy (>=1.7,<2.0)
Requires-Dist: torch (>=1.12.1,<1.13)
Requires-Dist: trash-cli (>=0.22,<0.23)
Requires-Dist: wandb (>=0.13.3,<0.14.0)
